Metadata-Version: 2.1
Name: twinpackagedani
Version: 0.1.1
Summary: Python package for my twinpackagedani.
Home-page: https://github.com/danielmen-mx/twinpackagedani
Download-URL: https://github.com/danielmen-mx/twinpackagedani/archive/0.1.1.tar.gz
Author: D.Mendez
Author-email: pablomen1131@gmail.com
Classifier: Programming Language :: Python :: 3
Classifier: License :: OSI Approved :: MIT License
Classifier: Operating System :: OS Independent
Requires-Python: >=3
License-File: LICENSE
